pyfdlock/__init__.py
pyfdlock/backend.py
pyfdlock/lock.py
pyfdlock-0.0.2.dist-info/LICENSE.md
pyfdlock-0.0.2.dist-info/METADATA
pyfdlock-0.0.2.dist-info/WHEEL
pyfdlock-0.0.2.dist-info/top_level.txt
pyfdlock-0.0.2.dist-info/RECORD
