Metadata-Version: 2.1
Name: pyfdlock
Version: 0.0.2
Summary: pyfdlock - file lock util
Home-page: https://github.com/kr-g/pyfdlock
Author: k.r. goger
Author-email: k.r.goger+pyfdlock@gmail.com
License: UNKNOWN
Keywords: python file locking lock unlock fcntl
Platform: UNKNOWN
Classifier: Development Status :: 3 - Alpha
Classifier: Operating System :: POSIX :: Linux
Classifier: Intended Audience :: Developers
Classifier: Programming Language :: Python :: 3
Classifier: License :: OSI Approved :: GNU Affero General Public License v3 or later (AGPLv3+)
Requires-Python: >=3.6
